aiocord/__init__.py
aiocord/client.py
aiocord/enums.py
aiocord/events.py
aiocord/helpers.py
aiocord/utils.py
aiocord/vendor.py
aiocord/widget.py
aiocord/gateway/__init__.py
aiocord/gateway/client.py
aiocord/gateway/enums.py
aiocord/gateway/errors.py
aiocord/gateway/helpers.py
aiocord/gateway/vital.py
aiocord/http/__init__.py
aiocord/http/client.py
aiocord/http/errors.py
aiocord/http/helpers.py
aiocord/http/routes.py
aiocord/model/__init__.py
aiocord/model/enums.py
aiocord/model/images.py
aiocord/model/mentions.py
aiocord/model/objects.py
aiocord/model/protocols.py
aiocord/model/responses.py
aiocord/model/types.py
aiocord/voice/__init__.py
aiocord/voice/audio.py
aiocord/voice/client.py
aiocord/voice/enums.py
aiocord/voice/errors.py
aiocord/voice/helpers.py
aiocord/voice/player.py
aiocord/voice/stream.py
aiocord/voice/vital.py
aiocord-2.1.0.dist-info/LICENSE
aiocord-2.1.0.dist-info/METADATA
aiocord-2.1.0.dist-info/WHEEL
aiocord-2.1.0.dist-info/entry_points.txt
aiocord-2.1.0.dist-info/top_level.txt
aiocord-2.1.0.dist-info/RECORD
