Metadata-Version: 2.1
Name: aiocord
Version: 2.1.0
Summary: A modern API wrapper for Discord.
Home-page: https://github.com/Exahilosys/aiocord
License: MIT
Requires-Python: >=3.11
License-File: LICENSE
Requires-Dist: yarl <2.0.0,>=1.9.1
Requires-Dist: aiohttp <4.0.0,>=3.8.4
Requires-Dist: vessel <5.0.0,>=4.2.0
Requires-Dist: pynacl <2.0.0,>=1.5.0
Provides-Extra: docs
Requires-Dist: sphinx ; extra == 'docs'
Requires-Dist: sphinx-paramlinks ; extra == 'docs'
Requires-Dist: sphinx-autodoc-typehints ; extra == 'docs'
